tox_docker/__init__.py
tox_docker/config.py
tox_docker/plugin.py
tox_docker/tests/__init__.py
tox_docker/tests/assert_containers_and_volumes_unchanged.py
tox_docker/tests/capture_containers_and_volumes.py
tox_docker/tests/test_containers.py
tox_docker/tests/test_env_vars.py
tox_docker/tests/test_gateway.py
tox_docker/tests/test_healthcheck.py
tox_docker/tests/test_images.py
tox_docker/tests/test_links.py
tox_docker/tests/test_ports.py
tox_docker/tests/test_volumes.py
tox_docker/tests/util.py
tox_docker_id-0.0.0.dist-info/LICENSE
tox_docker_id-0.0.0.dist-info/METADATA
tox_docker_id-0.0.0.dist-info/WHEEL
tox_docker_id-0.0.0.dist-info/entry_points.txt
tox_docker_id-0.0.0.dist-info/top_level.txt
tox_docker_id-0.0.0.dist-info/RECORD
