Metadata-Version: 2.1
Name: tox-docker-id
Version: 0.0.0
Summary: Manage lifecycle of docker containers during Tox test runs (patched version)
Home-page: https://github.com/d9pouces/tox-docker
Maintainer: Matthieu Gallet
Maintainer-email: github@19pouces.net
Classifier: Development Status :: 5 - Production/Stable
Classifier: Environment :: Plugins
Classifier: Intended Audience :: Developers
Classifier: License :: OSI Approved :: BSD License
Classifier: Programming Language :: Python :: 3.8
Classifier: Programming Language :: Python :: 3.9
Classifier: Programming Language :: Python :: 3.10
Classifier: Programming Language :: Python :: 3.11
Classifier: Programming Language :: Python :: 3.12
Classifier: Programming Language :: Python :: 3.13
Classifier: Topic :: Software Development :: Testing
License-File: LICENSE
Requires-Dist: docker<8.0,>=4.0
Requires-Dist: tox<5.0,>=4.0.0
